wizard_template/__init__.py
wizard_template/_version.py
wizard_template/core.py
wizard_template/py.typed
wizard_template-0.4.0.dist-info/METADATA
wizard_template-0.4.0.dist-info/WHEEL
wizard_template-0.4.0.dist-info/licenses/LICENSE
wizard_template-0.4.0.dist-info/RECORD
